pyinstallerx/PythonLibInstaller.py
pyinstallerx/__init__.py
pyinstallerx-1.0.0.dist-info/METADATA
pyinstallerx-1.0.0.dist-info/WHEEL
pyinstallerx-1.0.0.dist-info/entry_points.txt
pyinstallerx-1.0.0.dist-info/top_level.txt
pyinstallerx-1.0.0.dist-info/RECORD
