Metadata-Version: 2.4
Name: pyinstallerx
Version: 1.0.0
Summary: Install, uninstall, and update Python packages programmatically.
Author: Kiran Soorya.R.S
Author-email: hemalathakiransoorya2099@gmail.com
License: MIT
Classifier: Programming Language :: Python :: 3
Classifier: Operating System :: OS Independent
Classifier: License :: OSI Approved :: MIT License
Requires-Python: >=3.6
Requires-Dist: setuptools
Dynamic: author
Dynamic: author-email
Dynamic: classifier
Dynamic: description
Dynamic: description-content-type
Dynamic: license
Dynamic: requires-dist
Dynamic: requires-python
Dynamic: summary
